cobald_hep_plugins/__init__.py
cobald_hep_plugins/example.py
cobald_hep_plugins/stopper.py
cobald_hep_plugins-0.12.1.dist-info/entry_points.txt
cobald_hep_plugins-0.12.1.dist-info/LICENSE
cobald_hep_plugins-0.12.1.dist-info/WHEEL
cobald_hep_plugins-0.12.1.dist-info/METADATA
cobald_hep_plugins-0.12.1.dist-info/RECORD
