Metadata-Version: 2.1
Name: cobald-hep-plugins
Version: 0.12.1
Summary: COBalD/TARDIS Plugins for High Energy Physics
Keywords: cobald,tardis,High Energy Physics
Maintainer-email: Max Fischer <maxfischer2781@gmail.com>, MatterMiners <matterminers@lists.kit.edu>
Requires-Python: ~=3.6
Classifier: Development Status :: 5 - Production/Stable
Classifier: Intended Audience :: Developers
Classifier: License :: OSI Approved :: MIT License
Classifier: Programming Language :: Python :: 3 :: Only
Classifier: Programming Language :: Python :: 3.6
Classifier: Programming Language :: Python :: 3.7
Classifier: Programming Language :: Python :: 3.8
Classifier: Programming Language :: Python :: 3.9
Classifier: Programming Language :: Python :: 3.10
Requires-Dist: cobald~=0.12
Requires-Dist: cobald-tardis
Requires-Dist: typing_extensions; python_version<'3.8'
Requires-Dist: sphinx ; extra == "doc"
Requires-Dist: pytest ; extra == "test"
Requires-Dist: flake8 ; extra == "test"
Requires-Dist: flake8-bugbear ; extra == "test"
Requires-Dist: black ; extra == "test" and ( implementation_name=='cpython')
Requires-Dist: coverage ; extra == "test"
Requires-Dist: pytest-cov ; extra == "test"
Requires-Dist: flake8-2020 ; extra == "test"
Requires-Dist: mypy ; extra == "test" and ( implementation_name=='cpython')
Project-URL: Documentation, https://cobald-hep-plugins.readthedocs.io/
Project-URL: Source, https://github.com/MatterMiners/cobald-hep-plugins
Provides-Extra: doc
Provides-Extra: test
